rlpython/__init__.py
rlpython/aliases.py
rlpython/command_line.py
rlpython/completion.py
rlpython/embed.py
rlpython/frontend.py
rlpython/logging.py
rlpython/protocol.py
rlpython/repl.py
rlpython/repl_client.py
rlpython/repl_connection.py
rlpython/repl_server.py
rlpython/templating.py
rlpython/commands/__init__.py
rlpython/commands/aliases.py
rlpython/commands/edit.py
rlpython/commands/loops.py
rlpython/commands/tasks.py
rlpython/commands/threads.py
rlpython/commands/unix_environment.py
rlpython/commands/variables.py
rlpython/runtimes/__init__.py
rlpython/runtimes/command_runtime.py
rlpython/runtimes/python_runtime.py
rlpython/runtimes/shell_runtime.py
rlpython/utils/__init__.py
rlpython/utils/argument_parser.py
rlpython/utils/asyncio_utils.py
rlpython/utils/attribute_table.py
rlpython/utils/editor.py
rlpython/utils/gc_utils.py
rlpython/utils/strings.py
rlpython/utils/table.py
rlpython/utils/url.py
rlpython-0.10.3.data/scripts/rlpython
rlpython-0.10.3.dist-info/LICENSE.txt
rlpython-0.10.3.dist-info/METADATA
rlpython-0.10.3.dist-info/WHEEL
rlpython-0.10.3.dist-info/top_level.txt
rlpython-0.10.3.dist-info/RECORD
