Metadata-Version: 2.1
Name: rlpython
Version: 0.10.3
Summary: GNU Readline based Python REPL without any external dependencies
Author-email: Florian Scherf <mail@florianscherf.de>
License: MIT License
Project-URL: Homepage, https://github.com/fscherf/rlpython
Project-URL: Repository, https://github.com/fscherf/rlpython
Project-URL: Bug Tracker, https://github.com/fscherf/rlpython/issues
Classifier: Development Status :: 3 - Alpha
Classifier: Environment :: Console
Classifier: Intended Audience :: Developers
Classifier: Topic :: Software Development :: Debuggers
Classifier: Topic :: System :: Monitoring
Classifier: Topic :: System :: Shells
Classifier: Topic :: Terminals
Classifier: Topic :: Utilities
Classifier: License :: OSI Approved :: MIT License
Classifier: Natural Language :: English
Classifier: Programming Language :: Python :: 3 :: Only
License-File: LICENSE.txt
Provides-Extra: packaging
Requires-Dist: build ; extra == 'packaging'
Requires-Dist: twine ; extra == 'packaging'
